[
    {
        "title": "adhan",
        "translations": [
            {
                "lang": "en",
                "title": "๐ What is Adhan?",
                "desc": "In Islam, Adhan is the call to prayer, announced from a mosque to notify Muslims that it is time for one of the five daily prayers. It is a reminder of Allahโs greatness and the importance of Salah (prayer). The person who calls the Adhan is known as the Muezzin."
            },
            {
                "lang": "ml",
                "title": "๐ เดเดฆเดพเตป เดเดจเตเดคเดพเดฃเต?",
                "desc": "เดเดธเตเดฒเดพเดฎเดฟเตฝ เดเดฆเดพเตป (เดเดธเดพเตป) เดเดจเตเดจเดคเต เดฎเตเดธเตเดฒเดฟเดเดเดณเต เดเดเตเดเต เดธเดฎเดฏ เดจเดฎเดธเตเดเดพเดฐเดเตเดเดณเดฟเดฒเตเดเตเดเต เดตเดฟเดณเดฟเดเตเดเตเดจเตเดจเดคเดฟเดจเดพเดฏเดฟ เดฎเดธเตเดเดฟเดฆเดฟเตฝ เดจเดฟเดจเตเดจเต เดตเดฟเดณเดฟเดเตเดเตเดชเดฑเดฏเตเดจเตเดจ เดตเดฟเดณเดฟเดฏเดพเดฃเต. เดเดคเต เดเดฒเตเดฒเดพเดนเตเดตเดฟเดจเตเดฑเต เดฎเดนเดคเตเดตเดตเตเด เดจเดฎเดธเตเดเดพเดฐเดคเตเดคเดฟเดจเตเดฑเต (เดธเดฒเดพเดนเต) เดชเตเดฐเดพเดงเดพเดจเตเดฏเดตเตเด เดเตผเดฎเตเดฎเดชเตเดชเตเดเตเดคเตเดคเตเดจเตเดจเต. เดเดฆเดพเตป เดตเดฟเดณเดฟเดเตเดเตเดจเตเดจเดตเดจเต เดฎเตเดเดฆเตเดฆเดฟเตป (เดฎเตเดฏเดธเตเดธเดฟเตป) เดเดจเตเดจเดพเดฃเต เดตเดฟเดณเดฟเดเตเดเตเดจเตเดจเดคเต."
            }
        ],
        "quran": [
            {
                "simplified": "ููุฅูุฐูุง ููุงุฏูููุชููู ุฅูููู ุงูุตููููุงุฉู ุงุชููุฎูุฐููููุง ููุฒูููุง ููููุนูุจูุง",
                "translation_json": "{'ml':'เดจเดฟเดเตเดเดณเตโ เดจเดฎเดธเตเดเดพเดฐเดคเตเดคเดฟเดฒเตเดเตเดเต เดตเดฟเดณเดฟเดเตเดเดพเดฒเตโ, เดเดตเดฐเตโ เดเดคเดฟเดจเต เดชเดฐเดฟเดนเดพเดธเดตเตเด เดเดณเดฟเดฏเดพเดเตเดเดฒเตเดฎเดพเดฏเดฟเดเตเดเดพเดฃเต เดเดพเดฃเตเดจเตเดจเดคเต.'}",
                "number_in_chapter": 58,
                "chapter": 5
            }
        ],
        "hadiths": [
            {
                "simplified": "ุฅูุฐูุง ุญูุถูุฑูุชู ุงูุตููููุงุฉู ููููููุคูุฐูููู ูููููู ุฃูุญูุฏููููู",
                "translation_json": "{'ml':'เดจเดฎเดธเตเดเดพเดฐเดคเตเดคเดฟเดจเตเดฑเต เดธเดฎเดฏเด เดเดฏเดพเตฝ เดจเดฟเดเตเดเดณเดฟเตฝ เดเดฐเดพเตพ เดเดฆเดพเตป เดตเดฟเดณเดฟเดเตเดเดเตเดเต.'}",
                "book_slug": "sahih-bukhari",
                "hadith_number": 604
            },
            {
                "simplified": "ุงููููุคูุฐููููููู ุฃูุทููููู ุงููููุงุณู ุฃูุนูููุงููุง ูููููู ุงููููููุงููุฉู",
                "translation_json": "{'ml':'เดฎเตเดเดฆเตเดฆเดฟเดจเตเดฎเดพเดฐเดพเดฃเต เดเดฟเดฏเดพเดฎเดคเตเดคเต เดฆเดฟเดจเดคเตเดคเดฟเตฝ เดเดฑเตเดฑเดตเตเด เดฆเตเตผเดเดฎเดพเดฏ เดเดดเตเดคเตเดคเตเดเดณเตเดณเตเดณเดตเตผ.'}",
                "book_slug": "sahih-muslim",
                "hadith_number": 387
            }
        ],
        "videos": [
            {
                "video_id": "3R2U2nSmR9k",
                "title": "{'ml':'เดเดฆเดพเดจเตเดฑเต เดชเตเดฐเดพเดงเดพเดจเตเดฏเด - เดเตเดคเตเดฌเดคเตเดคเต'}"
            },
            {
                "video_id": "hVwxBv3ecb8",
                "title": "{'ml':'เดเดฆเดพเตป - เดตเดฟเดถเดฆเตเดเดฐเดฃเด'}"
            }
        ]
    }
]
